groundlight_openapi_client/__init__.py
groundlight_openapi_client/api/__init__.py
groundlight_openapi_client/api/actions_api.py
groundlight_openapi_client/api/detector_groups_api.py
groundlight_openapi_client/api/detector_reset_api.py
groundlight_openapi_client/api/detectors_api.py
groundlight_openapi_client/api/edge_api.py
groundlight_openapi_client/api/image_queries_api.py
groundlight_openapi_client/api/labels_api.py
groundlight_openapi_client/api/month_to_date_account_info_api.py
groundlight_openapi_client/api/notes_api.py
groundlight_openapi_client/api/user_api.py
groundlight_openapi_client/api_client.py
groundlight_openapi_client/apis/__init__.py
groundlight_openapi_client/configuration.py
groundlight_openapi_client/exceptions.py
groundlight_openapi_client/model/__init__.py
groundlight_openapi_client/model/account_month_to_date_info.py
groundlight_openapi_client/model/action.py
groundlight_openapi_client/model/action_list.py
groundlight_openapi_client/model/action_request.py
groundlight_openapi_client/model/all_notes.py
groundlight_openapi_client/model/annotations_requested_enum.py
groundlight_openapi_client/model/b_box_geometry.py
groundlight_openapi_client/model/b_box_geometry_request.py
groundlight_openapi_client/model/binary_classification_result.py
groundlight_openapi_client/model/blank_enum.py
groundlight_openapi_client/model/bounding_box_label_enum.py
groundlight_openapi_client/model/bounding_box_mode_configuration.py
groundlight_openapi_client/model/bounding_box_result.py
groundlight_openapi_client/model/channel_enum.py
groundlight_openapi_client/model/condition.py
groundlight_openapi_client/model/condition_request.py
groundlight_openapi_client/model/count_mode_configuration.py
groundlight_openapi_client/model/count_mode_configuration_serializer.py
groundlight_openapi_client/model/counting_result.py
groundlight_openapi_client/model/detector.py
groundlight_openapi_client/model/detector_creation_input_request.py
groundlight-0.23.3.dist-info/LICENSE
groundlight-0.23.3.dist-info/METADATA
groundlight-0.23.3.dist-info/WHEEL
groundlight-0.23.3.dist-info/entry_points.txt
groundlight-0.23.3.dist-info/RECORD
