Metadata-Version: 2.3
Name: groundlight
Version: 0.23.3
Summary: Build computer vision systems using natural language with Groundlight
License: MIT
Author: Groundlight AI
Author-email: support@groundlight.ai
Requires-Python: >=3.9,<4.0
Classifier: License :: OSI Approved :: MIT License
Classifier: Programming Language :: Python :: 3
Classifier: Programming Language :: Python :: 3.9
Classifier: Programming Language :: Python :: 3.10
Classifier: Programming Language :: Python :: 3.11
Classifier: Programming Language :: Python :: 3.12
Classifier: Programming Language :: Python :: 3.13
Requires-Dist: certifi (>=2023.7.22)
Requires-Dist: frozendict (>=2.3.2,<3.0.0)
Requires-Dist: pillow (>=11.0.0)
Requires-Dist: pydantic (>=2.0.0,<3.0.0)
Requires-Dist: python-dateutil (>=2.9.0,<3.0.0)
Requires-Dist: requests (>=2.28.2,<3.0.0)
Requires-Dist: typer (>=0.15.4,<0.16.0)
Requires-Dist: urllib3 (>=2.5.0,<3.0.0)
Project-URL: Homepage, https://code.groundlight.ai/python-sdk
